setup.py
pynetz/__init__.py
pynetz/network.py
pynetz.egg-info/PKG-INFO
pynetz.egg-info/SOURCES.txt
pynetz.egg-info/dependency_links.txt
pynetz.egg-info/not-zip-safe
pynetz.egg-info/requires.txt
pynetz.egg-info/top_level.txt