Metadata-Version: 1.0
Name: pynetz
Version: 0.1
Summary: A simple yet powerful Python Neural Network Implementation
Home-page: http://github.com/vdegenova/pynetz
Author: Vinny DeGenova
Author-email: vdegenova@gmail.com
License: MIT
Platform: UNKNOWN
